{
  "@context": "http://iiif.io/api/presentation/3/context.json",
  "id": "https://zillingworth.github.io/the-kindergarten-teacher-poetry/the-bull-read-by-lisa/canvas-1/canvas/narrative.json",
  "type": "AnnotationPage",
  "label": "Narrative",
  "items": [
    {
      "@context": "http://www.w3.org/ns/anno.jsonld",
      "id": "https://zillingworth.github.io/the-kindergarten-teacher-poetry/the-bull-read-by-lisa/canvas-1/canvas/narrative-annotation-0.json",
      "type": "Annotation",
      "motivation": [
        "supplementing",
        "commenting"
      ],
      "body": {
        "type": "TextualBody",
        "value": "Lisa finishes reading poem and puts down the paper. Her classmates look around seeming annoyed. ",
        "format": "text/plain"
      },
      "target": {
        "source": "https://zillingworth.github.io/the-kindergarten-teacher-poetry/the-bull-read-by-lisa/canvas-1/canvas",
        "selector": {
          "type": "PointSelector",
          "t": "53.14"
        }
      }
    }
  ]
}